[{"word": "Filing status m a", "bounding_box": [73.0, 158.0, 239.0, 134.0]}, {"word": "Mame", "bounding_box": [509.0, 155.0, 563.0, 143.0]}, {"word": "onetkony", "bounding_box": [73.0, 181.0, 163.0, 160.0]}, {"word": "eneboxt", "bounding_box": [76.0, 198.0, 146.0, 180.0]}, {"word": "I yot checkeu the Mr's bax errlarthename of vo", "bounding_box": [194.0, 199.0, 567.0, 174.0]}, {"word": "pe son s a chnd hu tat yot dependeny", "bounding_box": [194.0, 222.0, 513.0, 199.0]}, {"word": "Hrst namariomicder", "bounding_box": [113.0, 246.0, 267.0, 229.0]}, {"word": " Yotr sociht secury numter.", "bounding_box": [975.0, 248.0, 1183.0, 222.0]}, {"word": "Prwell", "bounding_box": [502.0, 268.0, 553.0, 251.0]}, {"word": "Spous's cooal cecurnyntambn", "bounding_box": [984.0, 294.0, 1194.0, 277.0]}, {"word": "Horme aroress (runber andereen fy(thate wF o.", "bounding_box": [78.0, 349.0, 442.0, 323.0]}, {"word": "IPrestentiht Flection Campatgn:", "bounding_box": [977.0, 349.0, 1206.0, 327.0]}, {"word": "04798 A1sor Pial ier", "bounding_box": [76.0, 371.0, 248.0, 349.0]}, {"word": "Hcheck hore t yoeror your.", "bounding_box": [966.0, 373.0, 1169.0, 347.0]}, {"word": "IGry town.or post cuien you hayn atoreurradsrs", "bounding_box": [78.0, 397.0, 430.0, 375.0]}, {"word": " pouse t fjina lointhy wan 93 t", "bounding_box": [977.0, 390.0, 1207.0, 368.0]}, {"word": "soaiso.cennoietes", "bounding_box": [426.0, 394.0, 556.0, 382.0]}, {"word": "petoy", "bounding_box": [592.0, 394.0, 632.0, 380.0]}, {"word": "West Bntreys", "bounding_box": [76.0, 421.0, 191.0, 399.0]}, {"word": "23784", "bounding_box": [885.0, 418.0, 932.0, 400.0]}, {"word": "hox below wit sot changer", "bounding_box": [977.0, 428.0, 1182.0, 402.0]}, {"word": "Toroin toimtm hane", "bounding_box": [80.0, 445.0, 232.0, 428.0]}, {"word": "jyour ax or e undy", "bounding_box": [968.0, 449.0, 1119.0, 423.0]}, {"word": "toutSpous", "bounding_box": [1025.0, 471.0, 1195.0, 447.0]}, {"word": "Digitaty", "bounding_box": [68.0, 502.0, 158.0, 478.0]}, {"word": "Assetst", "bounding_box": [71.0, 525.0, 153.0, 502.0]}, {"word": "wexchange grt onotherwsaaispose of a digta asset lorajiorcial", "bounding_box": [175.0, 524.0, 698.0, 502.0]}, {"word": "dlaialassetrSeenstrictionsa", "bounding_box": [792.0, 519.0, 1036.0, 502.0]}, {"word": "Ade/Bimdness You awere horh baore Jaauarye hg58", "bounding_box": [73.0, 612.0, 527.0, 586.0]}, {"word": "Debendents yss instuctonsyt", "bounding_box": [73.0, 638.0, 336.0, 615.0]}, {"word": "If more..", "bounding_box": [73.0, 667.0, 151.0, 641.0]}, {"word": "Toisatnan", "bounding_box": [341.0, 658.0, 433.0, 639.0]}, {"word": "srtmber", "bounding_box": [613.0, 655.0, 670.0, 638.0]}, {"word": "ohetax oredt", "bounding_box": [896.0, 658.0, 1008.0, 641.0]}, {"word": "Credttonahst.depehjer", "bounding_box": [1034.0, 658.0, 1194.0, 641.0]}, {"word": "Debondents", "bounding_box": [73.0, 703.0, 170.0, 684.0]}, {"word": "and.cherk", "bounding_box": [71.0, 739.0, 159.0, 720.0]}, {"word": "nere.", "bounding_box": [73.0, 756.0, 113.0, 742.0]}, {"word": "incomer", "bounding_box": [69.0, 800.0, 174.0, 771.0]}, {"word": "jat TotaPamouet fonFomo.2 box 1 laee instr uciorat", "bounding_box": [201.0, 787.0, 657.0, 765.0]}, {"word": "Ha", "bounding_box": [1022.0, 784.0, 1041.0, 770.0]}, {"word": "H. Hausehord embloyoa wages nor reported or Formst w.", "bounding_box": [223.0, 813.0, 665.0, 791.0]}, {"word": "Anachforms", "bounding_box": [73.0, 830.0, 177.0, 809.0]}, {"word": "Tp hoone not reporea Onnne ta sce ntruatoh.", "bounding_box": [230.0, 839.0, 622.0, 816.0]}, {"word": "W hereAlso", "bounding_box": [71.0, 849.0, 177.0, 830.0]}, {"word": "atachFoey", "bounding_box": [73.0, 866.0, 175.0, 849.0]}, {"word": "W-2Gand", "bounding_box": [69.0, 885.0, 151.0, 862.0]}, {"word": "1000-1", "bounding_box": [73.0, 901.0, 166.0, 882.0]}, {"word": "SHnpioyer orovoed ao apton nanents tromFonttaosg Jne", "bounding_box": [229.0, 913.0, 677.0, 887.0]}, {"word": "wanwithbed.", "bounding_box": [73.0, 920.0, 175.0, 901.0]}, {"word": "Wages fom fo m aso fne 6 y", "bounding_box": [230.0, 940.0, 477.0, 913.0]}, {"word": "Hyotdanors", "bounding_box": [71.0, 942.0, 170.0, 925.0]}, {"word": "gotuTomy", "bounding_box": [73.0, 959.0, 156.0, 942.0]}, {"word": "rother earned ncorne fes metctionts.", "bounding_box": [232.0, 964.0, 577.0, 938.0]}, {"word": "Nontao.abte.combal pay eenton (soo instinctigrs)", "bounding_box": [232.0, 988.0, 615.0, 962.0]}, {"word": "tretns", "bounding_box": [90.0, 992.0, 147.0, 980.0]}, {"word": "Adahres ia throtominy", "bounding_box": [232.0, 1012.0, 430.0, 990.0]}, {"word": "Atach Sohe", "bounding_box": [71.0, 1037.0, 163.0, 1016.0]}, {"word": "Taenxenot interest", "bounding_box": [237.0, 1037.0, 392.0, 1014.0]}, {"word": "PaaQuanedtdhdaends", "bounding_box": [194.0, 1062.0, 386.0, 1040.0]}, {"word": "3a", "bounding_box": [489.0, 1060.0, 516.0, 1040.0]}, {"word": "h.Ordnary.cmcr", "bounding_box": [698.0, 1062.0, 844.0, 1040.0]}, {"word": "h Taxutie aneont", "bounding_box": [700.0, 1088.0, 845.0, 1066.0]}, {"word": "tandarc", "bounding_box": [78.0, 1112.0, 130.0, 1095.0]}, {"word": "Casopertions.and anmte", "bounding_box": [199.0, 1112.0, 404.0, 1090.0]}, {"word": "t Tax ata amount", "bounding_box": [693.0, 1114.0, 847.0, 1091.0]}, {"word": "Doductiontors", "bounding_box": [69.0, 1129.0, 172.0, 1112.0]}, {"word": "barusccial scotuty buneits", "bounding_box": [197.0, 1138.0, 411.0, 1115.0]}, {"word": "Mariedtilrng", "bounding_box": [74.0, 1164.0, 156.0, 1146.0]}, {"word": "It you oest to ds ina un?", "bounding_box": [223.0, 1164.0, 449.0, 1141.0]}, {"word": "Sunreleofonmethod oreokharotgesnethichicms", "bounding_box": [445.0, 1160.0, 828.0, 1143.0]}, {"word": "12950", "bounding_box": [81.0, 1191.0, 132.0, 1174.0]}, {"word": "other.income rom Goheouin 1 line 1det", "bounding_box": [230.0, 1214.0, 546.0, 1188.0]}, {"word": "Cintiy", "bounding_box": [80.0, 1224.0, 113.0, 1212.0]}, {"word": "Adu Tres2b Hos4br5b6a7 andB Tnisne your total jbcome", "bounding_box": [237.0, 1239.0, 747.0, 1217.0]}, {"word": "oranvin", "bounding_box": [80.0, 1236.0, 130.0, 1224.0]}, {"word": "hnasp", "bounding_box": [80.0, 1255.0, 149.0, 1238.0]}, {"word": "Achsimortaioihopme fom SchacpleT le 2n", "bounding_box": [237.0, 1260.0, 599.0, 1243.0]}, {"word": "ecnntact", "bounding_box": [230.0, 1284.0, 307.0, 1268.0]}, {"word": "sntehamdanoricrooor", "bounding_box": [232.0, 1308.0, 424.0, 1296.0]}, {"word": "touaed buannss fncome deduttion rom Fou gapo oafomboget", "bounding_box": [222.0, 1337.0, 757.0, 1315.0]}, {"word": "subtract me", "bounding_box": [243.0, 1384.0, 336.0, 1366.0]}, {"word": "ondpaperworkPeduation Act Notice", "bounding_box": [265.0, 1437.0, 532.0, 1420.0]}, {"word": "oaseparare", "bounding_box": [537.0, 1433.0, 634.0, 1421.0]}]