[{"word": "Name Amanda Doe", "bounding_box": [30.0, 88.0, 112.0, 75.0]}, {"word": "Business Phone x2225559999", "bounding_box": [298.0, 87.0, 460.0, 74.0]}, {"word": "Home Address 444 Birch Dr", "bounding_box": [29.0, 115.0, 143.0, 97.0]}, {"word": "Home Phone xi-x", "bounding_box": [302.0, 114.0, 409.0, 101.0]}, {"word": "City,State,&Zip Code Meadowview,CA.97531", "bounding_box": [31.0, 141.0, 217.0, 128.0]}, {"word": "Business Name of Applicant/BorrowerWilson &Sons", "bounding_box": [30.0, 171.0, 240.0, 156.0]}, {"word": "Business Address f ciferent than home acdress888 Seventh S", "bounding_box": [29.0, 200.0, 274.0, 185.0]}, {"word": "This information is current as of [month/day/year]7/24/2022", "bounding_box": [30.0, 251.0, 267.0, 238.0]}, {"word": "within 90days of submission for 7a/504/SBG/ODA/WOSB or within 30 days of submission for 8aBD)", "bounding_box": [30.0, 263.0, 393.0, 250.0]}, {"word": "WOSB applicant only,Married", "bounding_box": [31.0, 284.0, 157.0, 272.0]}, {"word": "Yes!", "bounding_box": [171.0, 282.0, 189.0, 275.0]}, {"word": "IN", "bounding_box": [200.0, 282.0, 211.0, 274.0]}, {"word": "ASSETS", "bounding_box": [130.0, 311.0, 167.0, 297.0]}, {"word": "(Omt Cents)", "bounding_box": [223.0, 310.0, 262.0, 299.0]}, {"word": "LIABILITIES", "bounding_box": [362.0, 310.0, 414.0, 296.0]}, {"word": "(Omit Certs)", "bounding_box": [451.0, 310.0, 490.0, 299.0]}, {"word": "Cash on Hand &in banks..", "bounding_box": [31.0, 330.0, 130.0, 317.0]}, {"word": "$40,000", "bounding_box": [198.0, 329.0, 234.0, 315.0]}, {"word": "Accounts Payable.", "bounding_box": [287.0, 331.0, 354.0, 317.0]}, {"word": "$0", "bounding_box": [433.0, 330.0, 455.0, 316.0]}, {"word": "Savings Accounts...", "bounding_box": [30.0, 343.0, 115.0, 328.0]}, {"word": "$24.000", "bounding_box": [199.0, 341.0, 235.0, 327.0]}, {"word": "Notes Payable to Bans and Othr..", "bounding_box": [286.0, 343.0, 440.0, 327.0]}, {"word": "3250,000", "bounding_box": [433.0, 342.0, 476.0, 326.0]}, {"word": "RA or Other Retirement Account", "bounding_box": [30.0, 353.0, 150.0, 339.0]}, {"word": "Describe in Section 5", "bounding_box": [41.0, 365.0, 125.0, 350.0]}, {"word": "$150,000", "bounding_box": [199.0, 351.0, 237.0, 341.0]}, {"word": "Describe in Section 2", "bounding_box": [297.0, 353.0, 381.0, 341.0]}, {"word": "Instaiment AccountAuto", "bounding_box": [287.0, 364.0, 384.0, 351.0]}, {"word": "$300,000", "bounding_box": [437.0, 362.0, 476.0, 348.0]}, {"word": "Accounts&Notes Receivable.", "bounding_box": [31.0, 376.0, 138.0, 363.0]}, {"word": "Mo.Payments", "bounding_box": [295.0, 377.0, 353.0, 361.0]}, {"word": "$500", "bounding_box": [365.0, 374.0, 389.0, 363.0]}, {"word": "Describe in Section 5", "bounding_box": [41.0, 388.0, 125.0, 373.0]}, {"word": "Instament Account Other..", "bounding_box": [286.0, 389.0, 395.0, 374.0]}, {"word": "LieInsuranceCash SurnderVaue Oy.", "bounding_box": [31.0, 400.0, 197.0, 386.0]}, {"word": "Mo. Payments", "bounding_box": [296.0, 401.0, 353.0, 385.0]}, {"word": "Descnibe in Section 8", "bounding_box": [41.0, 412.0, 125.0, 397.0]}, {"word": "Loans Against Life Insurance", "bounding_box": [287.0, 411.0, 397.0, 399.0]}, {"word": "Stocks and Bonds....", "bounding_box": [31.0, 421.0, 108.0, 410.0]}, {"word": "$120,000", "bounding_box": [200.0, 419.0, 238.0, 409.0]}, {"word": "Mortgages on Real Estate.", "bounding_box": [287.0, 422.0, 383.0, 410.0]}, {"word": "$300.000", "bounding_box": [439.0, 423.0, 477.0, 410.0]}, {"word": "Describe in Section 3", "bounding_box": [41.0, 434.0, 124.0, 421.0]}, {"word": "$350,000", "bounding_box": [199.0, 444.0, 240.0, 430.0]}, {"word": "Descnibe in Section 4", "bounding_box": [298.0, 434.0, 381.0, 421.0]}, {"word": "Real Estate......", "bounding_box": [31.0, 444.0, 97.0, 433.0]}, {"word": "Unpaid Taxes....", "bounding_box": [288.0, 444.0, 348.0, 433.0]}, {"word": "$100,000", "bounding_box": [439.0, 443.0, 477.0, 432.0]}, {"word": "Describe in Section 4", "bounding_box": [41.0, 457.0, 124.0, 444.0]}, {"word": "$50,000", "bounding_box": [199.0, 468.0, 236.0, 454.0]}, {"word": "OthrLiabites.", "bounding_box": [286.0, 470.0, 362.0, 454.0]}, {"word": "Descnbe in Section 6", "bounding_box": [298.0, 456.0, 378.0, 446.0]}, {"word": "Automobiles......", "bounding_box": [32.0, 468.0, 93.0, 457.0]}, {"word": "Descibe in Section 5,and include", "bounding_box": [40.0, 479.0, 163.0, 467.0]}, {"word": "(Describe in Section 7", "bounding_box": [296.0, 480.0, 381.0, 466.0]}, {"word": "YeariMake/Model)", "bounding_box": [40.0, 492.0, 109.0, 476.0]}, {"word": "Total Liabie", "bounding_box": [284.0, 492.0, 344.0, 476.0]}, {"word": "$650.000", "bounding_box": [439.0, 491.0, 480.0, 477.0]}, {"word": "Other Personal Property", "bounding_box": [31.0, 503.0, 119.0, 488.0]}, {"word": "$25.000", "bounding_box": [199.0, 502.0, 237.0, 488.0]}, {"word": "Net Worth...", "bounding_box": [286.0, 503.0, 336.0, 489.0]}, {"word": "$800.000", "bounding_box": [441.0, 502.0, 478.0, 491.0]}, {"word": "Describe in Section 5", "bounding_box": [41.0, 515.0, 125.0, 502.0]}, {"word": "Other Assets....", "bounding_box": [32.0, 525.0, 91.0, 514.0]}, {"word": "$110,000", "bounding_box": [201.0, 524.0, 239.0, 513.0]}, {"word": "Total", "bounding_box": [375.0, 525.0, 398.0, 513.0]}, {"word": "S839.000", "bounding_box": [440.0, 525.0, 482.0, 509.0]}, {"word": "Describe in Section 5", "bounding_box": [41.0, 537.0, 125.0, 525.0]}, {"word": "$839,000", "bounding_box": [200.0, 547.0, 240.0, 534.0]}, {"word": "Must equal total in assets column.", "bounding_box": [375.0, 537.0, 495.0, 525.0]}, {"word": "Total", "bounding_box": [160.0, 547.0, 183.0, 536.0]}, {"word": "Section 1.Source of Income.", "bounding_box": [30.0, 569.0, 155.0, 553.0]}, {"word": "Contingent Liabilities", "bounding_box": [288.0, 569.0, 375.0, 554.0]}, {"word": "$150,000.00", "bounding_box": [203.0, 587.0, 253.0, 576.0]}, {"word": "As Endorser or Co-Maker", "bounding_box": [287.0, 590.0, 383.0, 576.0]}, {"word": "$0.00", "bounding_box": [443.0, 588.0, 470.0, 576.0]}, {"word": "Net Investment Income", "bounding_box": [31.0, 603.0, 114.0, 591.0]}, {"word": "$20,000.00", "bounding_box": [202.0, 601.0, 250.0, 588.0]}, {"word": "Legal Claims &Judgments..", "bounding_box": [287.0, 603.0, 390.0, 591.0]}, {"word": "$0.00", "bounding_box": [442.0, 603.0, 471.0, 589.0]}, {"word": "Real Estate Income.", "bounding_box": [32.0, 616.0, 106.0, 605.0]}, {"word": "$0.00", "bounding_box": [204.0, 615.0, 230.0, 603.0]}, {"word": "Provision for Federal Income Tax", "bounding_box": [287.0, 617.0, 406.0, 604.0]}, {"word": "$0.00", "bounding_box": [442.0, 617.0, 471.0, 604.0]}, {"word": "Other Income Describe below", "bounding_box": [30.0, 632.0, 142.0, 617.0]}, {"word": "$0.00", "bounding_box": [204.0, 629.0, 231.0, 617.0]}, {"word": "Other Special Debt...", "bounding_box": [289.0, 631.0, 364.0, 620.0]}, {"word": "$0.00", "bounding_box": [442.0, 631.0, 471.0, 618.0]}, {"word": "Decripion of Other ncome in Section 1 Anyrh sipo paymentshoudtbe ddinOt nc eitided taveh", "bounding_box": [27.0, 659.0, 491.0, 643.0]}, {"word": "poymensco.nedioward ibealincome", "bounding_box": [30.0, 665.0, 137.0, 659.0]}, {"word": "SBA Form 413(05-21Previous Editions Obsolete", "bounding_box": [43.0, 857.0, 225.0, 848.0]}, {"word": "Page 2", "bounding_box": [422.0, 859.0, 451.0, 847.0]}]