[{"word": "Nane  Michadl Doe?", "bounding_box": [74.0, 163.0, 272.0, 134.0]}, {"word": "Businezs Phone 9w.aw5.2225559999", "bounding_box": [722.0, 162.0, 1116.0, 137.0]}, {"word": "Home Address 999 Qak St s.", "bounding_box": [74.0, 217.0, 355.0, 178.0]}, {"word": "Home  hone.", "bounding_box": [729.0, 213.0, 866.0, 187.0]}, {"word": "City, State, & Zip Code Ookdale 13579", "bounding_box": [74.0, 266.0, 466.0, 237.0]}, {"word": " Busihess Name ot ApplicantiBorrower Doo Corp.", "bounding_box": [71.0, 325.0, 537.0, 289.0]}, {"word": "Business Address rdiierent than home aadres 777 Eigntty St", "bounding_box": [73.0, 375.0, 648.0, 344.0]}, {"word": "This imformationis current as of fnomttvdav/year1 1/24/2022.:", "bounding_box": [74.0, 468.0, 664.0, 442.0]}, {"word": "fwithih 90 -fays of submistior for 7(a)/504/SBcrODAWOsB o% within 30 days of submissjon for 3(g} Bb)", "bounding_box": [71.0, 493.0, 949.0, 462.0]}, {"word": "ASSETS", "bounding_box": [308.0, 583.0, 405.0, 553.0]}, {"word": "MLIARIUTISS", "bounding_box": [861.0, 579.0, 994.0, 555.0]}, {"word": "tomit c66tsy-", "bounding_box": [1084.0, 583.0, 1196.0, 555.0]}, {"word": "Cash on Hand d in banke", "bounding_box": [78.0, 617.0, 308.0, 593.0]}, {"word": "40.000", "bounding_box": [474.0, 614.0, 569.0, 584.0]}, {"word": "Accouints Payable.", "bounding_box": [698.0, 617.0, 861.0, 593.0]}, {"word": "Oavinas Accountswus", "bounding_box": [76.0, 638.0, 303.0, 615.0]}, {"word": "Notes Payable lo Banks and Oihers..", "bounding_box": [695.0, 638.0, 1010.0, 614.0]}, {"word": "$ 2507000", "bounding_box": [1057.0, 636.0, 1149.0, 612.0]}, {"word": "TRA or otherReremant Accoun", "bounding_box": [76.0, 660.0, 364.0, 638.0]}, {"word": "3 159 000.", "bounding_box": [478.0, 662.0, 577.0, 632.0]}, {"word": "ADesaribe insection o", "bounding_box": [700.0, 660.0, 927.0, 634.0]}, {"word": "(bescrbejh Spction.5)", "bounding_box": [81.0, 682.0, 305.0, 655.0]}, {"word": "Instalmen Account (Auto).):", "bounding_box": [695.0, 681.0, 932.0, 658.0]}, {"word": "Sto0o.c00", "bounding_box": [1058.0, 677.0, 1168.0, 653.0]}, {"word": "Accounts t Notes Roceivable?", "bounding_box": [76.0, 703.0, 338.0, 679.0]}, {"word": "MoPaymenta ", "bounding_box": [714.0, 703.0, 864.0, 681.0]}, {"word": "51500", "bounding_box": [868.0, 700.0, 939.0, 681.0]}, {"word": "Deshrpe m sectonJy", "bounding_box": [102.0, 724.0, 314.0, 701.0]}, {"word": "testaiment Account (ther s):", "bounding_box": [696.0, 725.0, 953.0, 703.0]}, {"word": "Life lestrance tcashsurenoerValie Only", "bounding_box": [78.0, 746.0, 452.0, 720.0]}, {"word": "wMor Raymentsy", "bounding_box": [698.0, 746.0, 875.0, 724.0]}, {"word": "CyDescribe n Section 31", "bounding_box": [85.0, 768.0, 324.0, 742.0]}, {"word": "Loan(s) Agamst Life insuranco.", "bounding_box": [689.0, 768.0, 958.0, 744.0]}, {"word": "Itooxs and Bondsst", "bounding_box": [76.0, 789.0, 246.0, 765.0]}, {"word": "$90.000", "bounding_box": [485.0, 785.0, 568.0, 761.0]}, {"word": " Mortdages on Real Fotate.", "bounding_box": [688.0, 789.0, 922.0, 763.0]}, {"word": "$.300.000", "bounding_box": [1058.0, 792.0, 1166.0, 763.0]}, {"word": "(Desenbe in Section 3)", "bounding_box": [85.0, 811.0, 300.0, 785.0]}, {"word": "tWDeserben sochon4y", "bounding_box": [705.0, 811.0, 927.0, 785.0]}, {"word": "350.000.", "bounding_box": [487.0, 830.0, 581.0, 802.0]}, {"word": "PS 800.000", "bounding_box": [1058.0, 830.0, 1159.0, 806.0]}, {"word": "pt(Describe In Section 4)", "bounding_box": [67.0, 856.0, 300.0, 828.0]}, {"word": "W(Desenbo in Scotion 6)", "bounding_box": [707.0, 854.0, 916.0, 832.0]}, {"word": "Automobiles.", "bounding_box": [74.0, 875.0, 198.0, 852.0]}, {"word": "3.57.000.", "bounding_box": [485.0, 873.0, 570.0, 847.0]}, {"word": "Oher Lrabilites n", "bounding_box": [689.0, 877.0, 868.0, 851.0]}, {"word": "YDeschbe n sector5.and ncude", "bounding_box": [95.0, 897.0, 398.0, 871.0]}, {"word": "(Descibe n Section7)", "bounding_box": [700.0, 897.0, 915.0, 871.0]}, {"word": "YearMakelModon ww", "bounding_box": [99.0, 918.0, 289.0, 895.0]}, {"word": "Total Liabilties:", "bounding_box": [696.0, 920.0, 830.0, 894.0]}, {"word": "6 00.000", "bounding_box": [1053.0, 916.0, 1155.0, 892.0]}, {"word": "other Pareonat Propory", "bounding_box": [73.0, 940.0, 298.0, 914.0]}, {"word": "$ 25.000", "bounding_box": [482.0, 940.0, 575.0, 911.0]}, {"word": "Nawaoh", "bounding_box": [683.0, 935.0, 807.0, 916.0]}, {"word": "$.300.000", "bounding_box": [1065.0, 942.0, 1166.0, 914.0]}, {"word": "aDesonbem Saotlonby", "bounding_box": [83.0, 961.0, 303.0, 938.0]}, {"word": "Other Assata.", "bounding_box": [74.0, 985.0, 269.0, 957.0]}, {"word": "S 110.000.", "bounding_box": [486.0, 984.0, 581.0, 952.0]}, {"word": "Torat", "bounding_box": [906.0, 983.0, 963.0, 959.0]}, {"word": "1$829.000.", "bounding_box": [1065.0, 981.0, 1164.0, 952.0]}, {"word": "HDesctbein Secton 5.", "bounding_box": [83.0, 1006.0, 303.0, 981.0]}, {"word": "Must asual totat mastele sdiumn.", "bounding_box": [904.0, 1004.0, 1195.0, 980.0]}, {"word": "Tbtat", "bounding_box": [390.0, 1023.0, 447.0, 1004.0]}, {"word": "839000", "bounding_box": [485.0, 1021.0, 579.0, 997.0]}, {"word": "Caaibntnesource ct Incomen", "bounding_box": [78.0, 1060.0, 376.0, 1036.0]}, {"word": "Contingent Liabiliues", "bounding_box": [698.0, 1062.0, 904.0, 1038.0]}, {"word": "100 000001", "bounding_box": [490.0, 1104.0, 660.0, 1069.0]}, {"word": "$0.00.3", "bounding_box": [1070.0, 1100.0, 1168.0, 1072.0]}, {"word": "Ner irvesimeni ncorre as", "bounding_box": [73.0, 1128.0, 296.0, 1102.0]}, {"word": "20.000.00", "bounding_box": [492.0, 1126.0, 676.0, 1100.0]}, {"word": "Wegal olams sJndomentst", "bounding_box": [693.0, 1129.0, 937.0, 1103.0]}, {"word": "5D.00", "bounding_box": [1071.0, 1126.0, 1197.0, 1102.0]}, {"word": "Real Fstato Incomehnt", "bounding_box": [78.0, 1153.0, 310.0, 1131.0]}, {"word": "5 0.00", "bounding_box": [493.0, 1152.0, 586.0, 1124.0]}, {"word": "000", "bounding_box": [1071.0, 1152.0, 1171.0, 1128.0]}, {"word": " oher Ppenal Debt t", "bounding_box": [684.0, 1186.0, 887.0, 1151.0]}, {"word": "poimetstoineu fonard otaiaren", "bounding_box": [64.0, 1250.0, 345.0, 1227.0]}, {"word": "SRAForm4rtes zrPrevibns Taitiois ohsoretey", "bounding_box": [90.0, 1605.0, 558.0, 1581.0]}]