[{"word": "Namey Jane Maunezs", "bounding_box": [74.0, 163.0, 289.0, 139.0]}, {"word": "Businesa Phone(xxx xxh.222555000g", "bounding_box": [721.0, 163.0, 1116.0, 139.0]}, {"word": "Home Address, doo Dak st.", "bounding_box": [74.0, 215.0, 341.0, 179.0]}, {"word": "Home Phonetyonxooon", "bounding_box": [728.0, 213.0, 989.0, 187.0]}, {"word": "City state  : Zip Code Springt old MA 97531", "bounding_box": [76.0, 266.0, 506.0, 237.0]}, {"word": "Business Name of Aoplicant/Sorrower e", "bounding_box": [74.0, 316.0, 473.0, 292.0]}, {"word": " Busirress Adaress (if cifferent than home address) 789 Market St", "bounding_box": [71.0, 375.0, 651.0, 344.0]}, {"word": "thrs informatron is currontas of Imonthdayyear 7/24/202zt:", "bounding_box": [78.0, 468.0, 657.0, 445.0]}, {"word": "(within 90 days er submission to-7(a)/504/SsG/ODAWOsE o) nthin 30 day/s or submis/on for 8(a) BD).", "bounding_box": [69.0, 493.0, 953.0, 462.0]}, {"word": "PASSETST", "bounding_box": [306.0, 583.0, 435.0, 551.0]}, {"word": "Tomittentsa", "bounding_box": [535.0, 579.0, 641.0, 562.0]}, {"word": "LIARILTTIESY", "bounding_box": [875.0, 579.0, 1005.0, 555.0]}, {"word": "Icashron Hand & In bankst", "bounding_box": [71.0, 617.0, 308.0, 591.0]}, {"word": "S 40.000", "bounding_box": [476.0, 614.0, 568.0, 590.0]}, {"word": "Acoounts Payabletyt.", "bounding_box": [689.0, 619.0, 901.0, 588.0]}, {"word": "SC", "bounding_box": [1057.0, 614.0, 1135.0, 590.0]}, {"word": "Savings Accounts.ason", "bounding_box": [74.0, 638.0, 282.0, 615.0]}, {"word": "T 24.000.", "bounding_box": [476.0, 636.0, 563.0, 612.0]}, {"word": "Noles Payabie to Hanks and Othore", "bounding_box": [693.0, 638.0, 996.0, 612.0]}, {"word": "1 250.600 t", "bounding_box": [1057.0, 638.0, 1157.0, 610.0]}, {"word": "RA pr Otier Retrement Account", "bounding_box": [74.0, 660.0, 362.0, 638.0]}, {"word": "$150.000", "bounding_box": [480.0, 658.0, 568.0, 634.0]}, {"word": "TLescuibe in Senon 2is", "bounding_box": [715.0, 660.0, 934.0, 638.0]}, {"word": "Descnbe in Section S.", "bounding_box": [92.0, 681.0, 310.0, 658.0]}, {"word": "Instalmienr Acchunt fAutoyas", "bounding_box": [693.0, 682.0, 960.0, 655.0]}, {"word": "300000", "bounding_box": [1058.0, 677.0, 1157.0, 653.0]}, {"word": "Accounts & Notas Racoivable.", "bounding_box": [76.0, 705.0, 333.0, 677.0]}, {"word": "Mo.Paymen  500", "bounding_box": [691.0, 706.0, 956.0, 675.0]}, {"word": "TDescribein Section 5e", "bounding_box": [90.0, 725.0, 317.0, 698.0]}, {"word": "Instalinent Aocount tOnerirs", "bounding_box": [693.0, 725.0, 958.0, 703.0]}, {"word": "Life InsurancotGash SurrenderVahieronivatie", "bounding_box": [80.0, 746.0, 482.0, 722.0]}, {"word": "MoPayments wr", "bounding_box": [710.0, 746.0, 871.0, 722.0]}, {"word": "(Deschbe T Spcuon 8).", "bounding_box": [95.0, 768.0, 305.0, 742.0]}, {"word": "Boan(s) Ag-imst are nsurence s", "bounding_box": [698.0, 768.0, 967.0, 744.0]}, {"word": "Stocks and Bondst", "bounding_box": [76.0, 789.0, 246.0, 765.0]}, {"word": "Mongagea on Roa Fstatett", "bounding_box": [695.0, 789.0, 941.0, 767.0]}, {"word": "0 310.000:", "bounding_box": [1062.0, 791.0, 1157.0, 761.0]}, {"word": "H(Describoin seotion 3).", "bounding_box": [80.0, 815.0, 324.0, 782.0]}, {"word": "yDescribe T Sectior 4y", "bounding_box": [705.0, 811.0, 920.0, 787.0]}, {"word": "Renl Estate", "bounding_box": [78.0, 830.0, 220.0, 808.0]}, {"word": "350.900", "bounding_box": [485.0, 831.0, 591.0, 799.0]}, {"word": "wunpaid Taxeorocen", "bounding_box": [686.0, 834.0, 878.0, 808.0]}, {"word": "$100.000.", "bounding_box": [1062.0, 832.0, 1156.0, 802.0]}, {"word": "HDeSorbo in 5ection 4", "bounding_box": [85.0, 854.0, 324.0, 830.0]}, {"word": "T(Descnbe In Seetior 6t", "bounding_box": [696.0, 854.0, 923.0, 828.0]}, {"word": "Automobitesy", "bounding_box": [67.0, 877.0, 213.0, 851.0]}, {"word": "S 50.000", "bounding_box": [481.0, 879.0, 572.0, 843.0]}, {"word": "(Describe in Sechion 5. hnd inchide:", "bounding_box": [83.0, 897.0, 397.0, 871.0]}, {"word": "T(Deronbe in Section 7))", "bounding_box": [707.0, 897.0, 927.0, 875.0]}, {"word": "Total abilitiost:", "bounding_box": [694.0, 920.0, 837.0, 892.0]}, {"word": "$650.000.", "bounding_box": [1063.0, 920.0, 1166.0, 888.0]}, {"word": "Other Personat Propeny", "bounding_box": [74.0, 942.0, 288.0, 914.0]}, {"word": "252000%", "bounding_box": [483.0, 938.0, 575.0, 914.0]}, {"word": "Net wont a", "bounding_box": [696.0, 937.0, 814.0, 918.0]}, {"word": "$200.000.", "bounding_box": [1067.0, 942.0, 1163.0, 912.0]}, {"word": "(Describe in Section ) ", "bounding_box": [80.0, 963.0, 312.0, 937.0]}, {"word": "$60,000", "bounding_box": [485.0, 982.0, 574.0, 954.0]}, {"word": "Total.", "bounding_box": [906.0, 983.0, 961.0, 959.0]}, {"word": "6839.000", "bounding_box": [1074.0, 980.0, 1162.0, 956.0]}, {"word": "HDescnbe in Secton ny", "bounding_box": [99.0, 1006.0, 305.0, 978.0]}, {"word": "SMust eaual totat i asstta coumte", "bounding_box": [904.0, 1005.0, 1204.0, 981.0]}, {"word": "Total:", "bounding_box": [390.0, 1026.0, 449.0, 1002.0]}, {"word": "$839000.", "bounding_box": [487.0, 1023.0, 582.0, 999.0]}, {"word": "Section I.Source of Income.", "bounding_box": [74.0, 1066.0, 374.0, 1035.0]}, {"word": "Conumgenti tabiites", "bounding_box": [695.0, 1066.0, 908.0, 1036.0]}, {"word": "1120.000.0073", "bounding_box": [490.0, 1097.0, 631.0, 1072.0]}, {"word": "As endorser or Co Maker.", "bounding_box": [689.0, 1100.0, 922.0, 1076.0]}, {"word": "$ 0.06270", "bounding_box": [1071.0, 1102.0, 1172.0, 1068.0]}, {"word": "Not invastmont Incomeswtn", "bounding_box": [76.0, 1129.0, 338.0, 1103.0]}, {"word": "$20.000.00", "bounding_box": [492.0, 1124.0, 648.0, 1100.0]}, {"word": "I t edal Claims t Judgments.", "bounding_box": [682.0, 1129.0, 932.0, 1102.0]}, {"word": "J Provision for Federal income Tax.", "bounding_box": [682.0, 1153.0, 989.0, 1127.0]}, {"word": "0.00.", "bounding_box": [1074.0, 1153.0, 1143.0, 1128.0]}, {"word": "Other tneome tUescribo below.", "bounding_box": [76.0, 1181.0, 353.0, 1158.0]}, {"word": "30.00", "bounding_box": [490.0, 1176.0, 572.0, 1157.0]}, {"word": "000", "bounding_box": [1072.0, 1179.0, 1142.0, 1155.0]}, {"word": "Desthiouon of Other lncone TnsectiongTAn", "bounding_box": [68.0, 1229.0, 502.0, 1205.0]}, {"word": "hony orchid subpor onynent stould npt be siscosed otone ycome uniessies t stedtg na stey pa.", "bounding_box": [492.0, 1231.0, 1220.0, 1207.0]}, {"word": "Ispaymenstountedrvart.otarincomeme", "bounding_box": [64.0, 1250.0, 357.0, 1225.0]}, {"word": "HBATo1n413 10520Prevo0T16ons Obsolete.", "bounding_box": [92.0, 1605.0, 551.0, 1581.0]}]